cozmox_sdk/__init__.py
cozmox_sdk/_base_client.py
cozmox_sdk/_client.py
cozmox_sdk/_compat.py
cozmox_sdk/_constants.py
cozmox_sdk/_exceptions.py
cozmox_sdk/_files.py
cozmox_sdk/_models.py
cozmox_sdk/_qs.py
cozmox_sdk/_resource.py
cozmox_sdk/_response.py
cozmox_sdk/_streaming.py
cozmox_sdk/_types.py
cozmox_sdk/_version.py
cozmox_sdk/py.typed
cozmox_sdk/_utils/__init__.py
cozmox_sdk/_utils/_logs.py
cozmox_sdk/_utils/_proxy.py
cozmox_sdk/_utils/_reflection.py
cozmox_sdk/_utils/_streams.py
cozmox_sdk/_utils/_sync.py
cozmox_sdk/_utils/_transform.py
cozmox_sdk/_utils/_typing.py
cozmox_sdk/_utils/_utils.py
cozmox_sdk/lib/.keep
cozmox_sdk/resources/__init__.py
cozmox_sdk/resources/nebula.py
cozmox_sdk/resources/outbound.py
cozmox_sdk/types/__init__.py
cozmox_sdk/types/nebula_hello_response.py
cozmox_sdk/types/outbound_create_call_params.py
cozmox_sdk/types/outbound_create_call_response.py
cozmox_sdk-1.0.0.dist-info/METADATA
cozmox_sdk-1.0.0.dist-info/WHEEL
cozmox_sdk-1.0.0.dist-info/licenses/LICENSE
cozmox_sdk-1.0.0.dist-info/RECORD
